cfn_custom_resource/__init__.py
cfn_custom_resource/decorator.py
cfn_custom_resource-1.0.1.dist-info/LICENSE
cfn_custom_resource-1.0.1.dist-info/METADATA
cfn_custom_resource-1.0.1.dist-info/WHEEL
cfn_custom_resource-1.0.1.dist-info/top_level.txt
cfn_custom_resource-1.0.1.dist-info/RECORD
