Metadata-Version: 2.1
Name: cfn-custom-resource
Version: 1.0.1
Summary: A helper lib for lambda based Custom Resources (AWS CloudFormation)
Home-page: https://bitbucket.org/atlassian/cfn-custom-resource
Author: Michael Sverdlik
Author-email: msverdlik@atlassian.com
License: Apache 2.0
Keywords: aws,cloudformation,lambda
Platform: any
Classifier: License :: OSI Approved :: Apache Software License
Classifier: Development Status :: 5 - Production/Stable
Classifier: Topic :: Software Development :: Libraries :: Python Modules
Classifier: Programming Language :: Python :: 3.6
Classifier: Programming Language :: Python :: 3.7
Provides-Extra: dev
Requires-Dist: tox ; extra == 'dev'
Requires-Dist: flake8 ; extra == 'dev'
Requires-Dist: pytest ; extra == 'dev'
Requires-Dist: pytest-localserver (==0.5.0) ; extra == 'dev'
